{
	"animations": [
		{
			"offsets": [
				0,
				0
			],
			"indices": [],
			"fps": 8,
			"anim": "singDOWN",
			"loop": false,
			"name": "down"
		},
		{
			"offsets": [
				0,
				0
			],
			"indices": [],
			"fps": 8,
			"anim": "singLEFT",
			"loop": false,
			"name": "left"
		},
		{
			"offsets": [
				0,
				0
			],
			"indices": [],
			"fps": 8,
			"anim": "idle",
			"loop": false,
			"name": "idle"
		},
		{
			"offsets": [
				0,
				0
			],
			"indices": [],
			"fps": 8,
			"anim": "singUP",
			"loop": false,
			"name": "up"
		},
		{
			"offsets": [
				0,
				0
			],
			"indices": [],
			"fps": 8,
			"anim": "singRIGHT",
			"loop": false,
			"name": "right"
		}
	],
	"no_antialiasing": true,
	"image": "characters/doyneBetter_sprited",
	"position": [
		0,
		350
	],
	"healthicon": "douyhe-pixel",
	"flip_x": false,
	"healthbar_colors": [
		255,
		255,
		255
	],
	"camera_position": [
		0,
		0
	],
	"sing_duration": 4,
	"scale": 10
}