{
	"animations": [
		{
			"offsets": [
				-700,
				-560
			],
			"loop": true,
			"fps": 12,
			"anim": "idle",
			"indices": [],
			"name": "awesome-ron idle"
		},
		{
			"offsets": [
				-695,
				-560
			],
			"loop": false,
			"fps": 8,
			"anim": "singLEFT",
			"indices": [],
			"name": "awesome-ron left"
		},
		{
			"loop": false,
			"offsets": [
				-700,
				-560
			],
			"anim": "singDOWN",
			"fps": 12,
			"name": "awesome-ron down",
			"indices": []
		},
		{
			"loop": false,
			"offsets": [
				-674,
				-550
			],
			"anim": "singUP",
			"fps": 12,
			"name": "awesome-ron up",
			"indices": []
		},
		{
			"loop": false,
			"offsets": [
				-700,
				-555
			],
			"anim": "singRIGHT",
			"fps": 12,
			"name": "awesome-ron right",
			"indices": []
		}
	],
	"no_antialiasing": true,
	"image": "characters/newcharstest/awesome-ron",
	"position": [
		-940,
		-330
	],
	"healthicon": "awesome-ron",
	"flip_x": false,
	"healthbar_colors": [
		255,
		255,
		0
	],
	"camera_position": [
		1020,
		700
	],
	"sing_duration": 4,
	"noteskin": "NOTE_assets",
	"scale": 1
}